{
  "project": "ThaiBev Call Center - Mock Data Redesign",
  "branchName": "feat/thaibev-mock-data",
  "description": "Recreate all mock data for ThaiBev Group companies (ThaiBev, Sermsuk, Oishi, KFC Thailand)",
  "userStories": [
    {
      "id": "TB-001",
      "title": "Update database schema with new business units and categories",
      "priority": 1,
      "phase": "Schema",
      "file": "lib/db/schema.ts",
      "description": "Update schema.ts with new ThaiBev-themed business units and categories.",
      "acceptanceCriteria": [
        "Add 8 new business units for ThaiBev Group",
        "Add 12 new F&B-relevant categories with subcategories",
        "Keep existing table structure intact",
        "npm run typecheck passes"
      ],
      "passes": true
    },
    {
      "id": "TB-002",
      "title": "Create ThaiBev case templates and summaries",
      "priority": 2,
      "phase": "Data",
      "file": "lib/db/seed-data.ts",
      "description": "Create new file with case templates, Thai names, product lists, and realistic summaries.",
      "acceptanceCriteria": [
        "Create lib/db/seed-data.ts with all template data",
        "Include 50+ unique case summary templates per BU",
        "Include Thai and English customer names",
        "Include product names for each BU",
        "Include branch/location names",
        "npm run typecheck passes"
      ],
      "passes": true
    },
    {
      "id": "TB-003",
      "title": "Rewrite seed.ts with ThaiBev data generation",
      "priority": 3,
      "phase": "Data",
      "file": "lib/db/seed.ts",
      "description": "Rewrite seed script to generate 2000+ cases with ThaiBev-themed data.",
      "acceptanceCriteria": [
        "Generate 2000+ cases across 8 business units",
        "Weighted distribution favoring KFC and Oishi (higher volume)",
        "Include 3 predictive alert scenarios",
        "Create realistic alert data",
        "Create trending topics for ThaiBev products",
        "npm run typecheck passes",
        "npm run db:seed runs successfully"
      ],
      "passes": true
    },
    {
      "id": "TB-004",
      "title": "Update filter components with new options",
      "priority": 4,
      "phase": "UI",
      "file": "components/cases/CaseFilters.tsx",
      "description": "Update CaseFilters and AlertFilters with new BU and category options.",
      "acceptanceCriteria": [
        "Update businessUnits array in CaseFilters.tsx",
        "Update categories array in CaseFilters.tsx",
        "Update businessUnits array in AlertFilters.tsx",
        "npm run typecheck passes",
        "npm run lint passes"
      ],
      "passes": true
    },
    {
      "id": "TB-005",
      "title": "Update chat responses for ThaiBev context",
      "priority": 5,
      "phase": "UI",
      "file": "lib/chatIntents.ts",
      "description": "Update AI chat assistant responses to understand ThaiBev context.",
      "acceptanceCriteria": [
        "Update parseUserQuery to recognize ThaiBev products",
        "Update filter suggestions for new BUs",
        "Add ThaiBev-specific quick responses",
        "npm run typecheck passes"
      ],
      "passes": true
    },
    {
      "id": "TB-006",
      "title": "Reseed database and verify data",
      "priority": 6,
      "phase": "Verification",
      "file": "lib/db/seed.ts",
      "description": "Run seed script and verify all data is correctly generated.",
      "acceptanceCriteria": [
        "npm run db:seed completes without errors",
        "Database contains 2000+ cases",
        "All 8 business units have cases",
        "Alerts are generated correctly",
        "Trending topics show ThaiBev products",
        "npm run build passes",
        "Verify in browser - cases show ThaiBev data"
      ],
      "passes": true
    }
  ]
}
